{
  "info": "base16-Material Lighter by Nate Peterson",
  "colors": {
    "accentcolor":                  "#FAFAFA",
    "button_background_active":     "#CCD7DA",
    "button_background_hover":      "#CCEAE7",
    "icons":                        "#80CBC4",
    "icons_attention":              "#6182B8",
    "tab_line":                     "#6182B8",
    "tab_loading":                  "#6182B8",
    "tab_selected":                 "#E7EAEC",
    "tab_text":                     "#80CBC4",
    "textcolor":                    "#80CBC4",
    "toolbar":                      "#E7EAEC",
    "toolbar_bottom_separator":     "#FAFAFA",
    "toolbar_field":                "#CCEAE7",
    "toolbar_field_border":         "#E7EAEC",
    "toolbar_field_separator":      "#E7EAEC",
    "toolbar_field_text":           "#80CBC4",
    "toolbar_text":                 "#80CBC4",
    "toolbar_top_separator":        "#E7EAEC",
    "toolbar_vertical_separator":   "#E7EAEC"
  }
}
